MANIFEST.in
VERSION
distribute_setup.py
setup.py
src/calabash/__init__.py
src/calabash/common.py
src/calabash/pipeline.py
src/calabash.egg-info/PKG-INFO
src/calabash.egg-info/SOURCES.txt
src/calabash.egg-info/dependency_links.txt
src/calabash.egg-info/top_level.txt