Metadata-Version: 1.0
Name: calabash
Version: 0.0.1
Summary: Bash-style pipelining syntax for Python generators.
Home-page: http://github.com/zacharyvoase/calabash
Author: Zachary Voase
Author-email: z@zacharyvoase.com
License: UNKNOWN
Platform: UNKNOWN
